printf.py
printf_package-0.5.0.dist-info/LICENSE
printf_package-0.5.0.dist-info/METADATA
printf_package-0.5.0.dist-info/WHEEL
printf_package-0.5.0.dist-info/top_level.txt
printf_package-0.5.0.dist-info/RECORD
