Metadata-Version: 2.1
Name: printf-package
Version: 0.5.0
Summary: A package for experiment printf function
Home-page: https://github.com/uchihamadara6969/printf-package
Author: Darked Nuke
Author-email: darkednuke@gmail.com
Classifier: Programming Language :: Python :: 3
Classifier: License :: OSI Approved :: MIT License
Classifier: Operating System :: OS Independent
Requires-Python: >=3.6
License-File: LICENSE
